<?xml version="1.0" encoding="Windows-1252"?>
<ArrayOfSortItemData xmlns:xsi="http://www.w3.org/2001/XMLSchema-instance" xmlns:xsd="http://www.w3.org/2001/XMLSchema">
  <SortItemData>
    <questionID>tut3</questionID>
    <stem>Sort which terms most describe you from the left to the right</stem>
    <sortAnswers>
      <SortAnswerData>
        <answerText>noob</answerText>
        <correctOrder>0</correctOrder>
      </SortAnswerData>
      <SortAnswerData>
        <answerText>casual gamer</answerText>
        <correctOrder>1</correctOrder>
      </SortAnswerData>
      <SortAnswerData>
        <answerText>core gamer</answerText>
        <correctOrder>2</correctOrder>
      </SortAnswerData>
      <SortAnswerData>
        <answerText>professional gamer</answerText>
        <correctOrder>3</correctOrder>
      </SortAnswerData>
    </sortAnswers>
  </SortItemData>
  <SortItemData>
    <questionID>sor0</questionID>
    <stem>Sort the words below alphabetically, from left to right</stem>
    <sortAnswers>
      <SortAnswerData>
        <answerText>craftsman</answerText>
        <correctOrder>1</correctOrder>
      </SortAnswerData>
      <SortAnswerData>
        <answerText>crank</answerText>
        <correctOrder>2</correctOrder>
      </SortAnswerData>
      <SortAnswerData>
        <answerText>cranky</answerText>
        <correctOrder>3</correctOrder>
      </SortAnswerData>
      <SortAnswerData>
        <answerText>craft</answerText>
        <correctOrder>0</correctOrder>
      </SortAnswerData>
    </sortAnswers>
  </SortItemData>
  <SortItemData>
    <questionID>sor1</questionID>
    <stem>Sort the words below alphabetically, from left to right</stem>
    <sortAnswers>
      <SortAnswerData>
        <answerText>trapeze</answerText>
        <correctOrder>0</correctOrder>
      </SortAnswerData>
      <SortAnswerData>
        <answerText>trapper</answerText>
        <correctOrder>1</correctOrder>
      </SortAnswerData>
      <SortAnswerData>
        <answerText>treatment</answerText>
        <correctOrder>3</correctOrder>
      </SortAnswerData>
      <SortAnswerData>
        <answerText>traveler</answerText>
        <correctOrder>2</correctOrder>
      </SortAnswerData>
    </sortAnswers>
  </SortItemData>
  <SortItemData>
    <questionID>sor2</questionID>
    <stem>Sort the words below alphabetically, from left to right</stem>
    <sortAnswers>
      <SortAnswerData>
        <answerText>runner</answerText>
        <correctOrder>2</correctOrder>
      </SortAnswerData>
      <SortAnswerData>
        <answerText>race</answerText>
        <correctOrder>0</correctOrder>
      </SortAnswerData>
      <SortAnswerData>
        <answerText>rush</answerText>
        <correctOrder>3</correctOrder>
      </SortAnswerData>
      <SortAnswerData>
        <answerText>ran</answerText>
        <correctOrder>1</correctOrder>
      </SortAnswerData>
    </sortAnswers>
  </SortItemData>
  <SortItemData>
    <questionID>sor3</questionID>
    <stem>Sort the words below alphabetically, from left to right</stem>
    <sortAnswers>
      <SortAnswerData>
        <answerText>own</answerText>
        <correctOrder>3</correctOrder>
      </SortAnswerData>
      <SortAnswerData>
        <answerText>oak</answerText>
        <correctOrder>0</correctOrder>
      </SortAnswerData>
      <SortAnswerData>
        <answerText>oar</answerText>
        <correctOrder>1</correctOrder>
      </SortAnswerData>
      <SortAnswerData>
        <answerText>owl</answerText>
        <correctOrder>2</correctOrder>
      </SortAnswerData>
    </sortAnswers>
  </SortItemData>
  <SortItemData>
    <questionID>sor4</questionID>
    <stem>Sort the words below alphabetically, from left to right</stem>
    <sortAnswers>
      <SortAnswerData>
        <answerText>dark</answerText>
        <correctOrder>3</correctOrder>
      </SortAnswerData>
      <SortAnswerData>
        <answerText>dandelion</answerText>
        <correctOrder>2</correctOrder>
      </SortAnswerData>
      <SortAnswerData>
        <answerText>daisy</answerText>
        <correctOrder>1</correctOrder>
      </SortAnswerData>
      <SortAnswerData>
        <answerText>daffodil</answerText>
        <correctOrder>0</correctOrder>
      </SortAnswerData>
    </sortAnswers>
  </SortItemData>
  <SortItemData>
    <questionID>sor5</questionID>
    <stem>Sort the words below alphabetically, from left to right</stem>
    <sortAnswers>
      <SortAnswerData>
        <answerText>sandal</answerText>
        <correctOrder>0</correctOrder>
      </SortAnswerData>
      <SortAnswerData>
        <answerText>send</answerText>
        <correctOrder>3</correctOrder>
      </SortAnswerData>
      <SortAnswerData>
        <answerText>seen</answerText>
        <correctOrder>2</correctOrder>
      </SortAnswerData>
      <SortAnswerData>
        <answerText>scare</answerText>
        <correctOrder>1</correctOrder>
      </SortAnswerData>
    </sortAnswers>
  </SortItemData>
  <SortItemData>
    <questionID>sor6</questionID>
    <stem>Sort the words below alphabetically, from left to right</stem>
    <sortAnswers>
      <SortAnswerData>
        <answerText>robin</answerText>
        <correctOrder>3</correctOrder>
      </SortAnswerData>
      <SortAnswerData>
        <answerText>rain</answerText>
        <correctOrder>0</correctOrder>
      </SortAnswerData>
      <SortAnswerData>
        <answerText>rainy</answerText>
        <correctOrder>2</correctOrder>
      </SortAnswerData>
      <SortAnswerData>
        <answerText>rainbow</answerText>
        <correctOrder>1</correctOrder>
      </SortAnswerData>
    </sortAnswers>
  </SortItemData>
  <SortItemData>
    <questionID>sor7</questionID>
    <stem>Sort the words below alphabetically, from left to right</stem>
    <sortAnswers>
      <SortAnswerData>
        <answerText>east</answerText>
        <correctOrder>0</correctOrder>
      </SortAnswerData>
      <SortAnswerData>
        <answerText>enter</answerText>
        <correctOrder>3</correctOrder>
      </SortAnswerData>
      <SortAnswerData>
        <answerText>easy</answerText>
        <correctOrder>1</correctOrder>
      </SortAnswerData>
      <SortAnswerData>
        <answerText>end</answerText>
        <correctOrder>2</correctOrder>
      </SortAnswerData>
    </sortAnswers>
  </SortItemData>
  <SortItemData>
    <questionID>sor8</questionID>
    <stem>Sort the words below alphabetically, from left to right</stem>
    <sortAnswers>
      <SortAnswerData>
        <answerText>garden</answerText>
        <correctOrder>0</correctOrder>
      </SortAnswerData>
      <SortAnswerData>
        <answerText>grass</answerText>
        <correctOrder>1</correctOrder>
      </SortAnswerData>
      <SortAnswerData>
        <answerText>grow</answerText>
        <correctOrder>3</correctOrder>
      </SortAnswerData>
      <SortAnswerData>
        <answerText>green</answerText>
        <correctOrder>2</correctOrder>
      </SortAnswerData>
    </sortAnswers>
  </SortItemData>
  <SortItemData>
    <questionID>sor9</questionID>
    <stem>Sort the words below alphabetically, from left to right</stem>
    <sortAnswers>
      <SortAnswerData>
        <answerText>truck</answerText>
        <correctOrder>1</correctOrder>
      </SortAnswerData>
      <SortAnswerData>
        <answerText>trek</answerText>
        <correctOrder>0</correctOrder>
      </SortAnswerData>
      <SortAnswerData>
        <answerText>truncate</answerText>
        <correctOrder>3</correctOrder>
      </SortAnswerData>
      <SortAnswerData>
        <answerText>truly</answerText>
        <correctOrder>2</correctOrder>
      </SortAnswerData>
    </sortAnswers>
  </SortItemData>
</ArrayOfSortItemData>